[
  {
    "id": "3gm7dnjs",
    "url": "https://x.com/La_Pla/status/1954718910584082931",
    "title": "(無題)",
    "comment": "タイトルなし再々テスト\r\n",
    "createdAt": 1756073013038,
    "ownerKey": "381f799d-0c46-4c5d-a667-12755a1e0ecb"
  },
  {
    "id": "n8wwnbf8",
    "url": "https://x.com/sGr2PCxP0hhZRmw/status/1956682565898924305",
    "title": "",
    "comment": "テキストのみのテスト",
    "handle": "町蔵",
    "createdAt": 1756073594127,
    "ownerKey": "381f799d-0c46-4c5d-a667-12755a1e0ecb"
  },
  {
    "id": "n9ltpqkn",
    "url": "https://x.com/okada_2019/status/1959411556334424506",
    "title": "",
    "comment": "画像つきのテスト",
    "handle": "町蔵",
    "createdAt": 1756073714625,
    "ownerKey": "381f799d-0c46-4c5d-a667-12755a1e0ecb"
  },
  {
    "id": "xiq8kmjh",
    "url": "https://yoshiko-sakurai.jp/2005/07/02/396",
    "title": "「　人口調査や研究書でも検証　ほぼ完璧に否定されている南京での“三〇万人虐殺”　」",
    "comment": "ブログ記事のテスト",
    "handle": "町蔵",
    "tags": [
      "中国人"
    ],
    "createdAt": 1756075022795,
    "ownerKey": "381f799d-0c46-4c5d-a667-12755a1e0ecb"
  },
  {
    "id": "p1xxc7hp",
    "url": "https://www.youtube.com/watch?v=HKPfestn2iY&ab_channel=FNN%E3%83%97%E3%83%A9%E3%82%A4%E3%83%A0%E3%82%AA%E3%83%B3%E3%83%A9%E3%82%A4%E3%83%B3",
    "title": "JR山手線車内で爆音響かせる外国人男性…渋谷駅ホームで突如“バク宙”　迷惑系インフルエンサーのファンが代々木公園に殺到も",
    "comment": "Youtubeのテスト",
    "tags": [
      "ニュース"
    ],
    "createdAt": 1756096206940,
    "ownerKey": "381f799d-0c46-4c5d-a667-12755a1e0ecb"
  },
  {
    "id": "8yp0l1f6",
    "url": "https://news.yahoo.co.jp/articles/486084bb5877074fa8bf73605926cb37ca78e8e8",
    "title": "「我慢の限界でした」温泉で騒ぐ外国人観光客に地元民がウンザリ。スタッフに注意され謝罪するまで（週刊SPA!）",
    "comment": "WEB記事テスト",
    "handle": "町蔵",
    "tags": [
      "政治/制度"
    ],
    "createdAt": 1756102787468,
    "ownerKey": "381f799d-0c46-4c5d-a667-12755a1e0ecb"
  },
  {
    "id": "ssclbh2s",
    "url": "https://www.sankei.com/article/20150605-HD3RQ7PAWNOVBPGQP2U4CNUSYA/",
    "title": "【伊勢志摩サミット】安倍首相「日本の美しい自然、豊かな文化・伝統を肌で感じてもらえる場所を…」",
    "comment": "産経新聞テスト",
    "tags": [
      "ニュース"
    ],
    "createdAt": 1756107604269,
    "ownerKey": "381f799d-0c46-4c5d-a667-12755a1e0ecb"
  },
  {
    "id": "1bn4ar72",
    "url": "https://www3.nhk.or.jp/news/html/20250825/k10014902491000.html",
    "title": "大川原化工機えん罪事件 遺族に警視庁と検察庁の幹部 直接謝罪",
    "comment": "NHKニュースのテスト",
    "tags": [
      "ニュース"
    ],
    "createdAt": 1756108058813,
    "ownerKey": "381f799d-0c46-4c5d-a667-12755a1e0ecb"
  },
  {
    "id": "s358flec",
    "url": "https://news.yahoo.co.jp/articles/b5df569d265e7deb5bd81dd7105fcdd09248f7ca",
    "title": "「とても美しいの」　日本を旅行したアメリカ人がずっと大切に保管　デザイン性の高さに驚いた意外なものとは（Hint-Pot）",
    "comment": "ヤフーのテスト",
    "tags": [
      "ニュース"
    ],
    "createdAt": 1756116620310,
    "ownerKey": "381f799d-0c46-4c5d-a667-12755a1e0ecb"
  },
  {
    "id": "28bzghdx",
    "url": "https://www.jiji.com/jc/article?k=2025082500099&g=int&utm_source=newsshowcase&utm_medium=gnews&utm_campaign=CDAQ_Jj1jajU3_gaGN3trN_d7t7brgEqEAgAKgcICjCW0d4KMKel1gE&utm_content=rundown",
    "title": "日印「２国間クレジット」実施へ　温室ガス削減、新エネ投資促進：時事ドットコム",
    "comment": "時事通信のテスト",
    "tags": [],
    "createdAt": 1756116668593,
    "ownerKey": "381f799d-0c46-4c5d-a667-12755a1e0ecb"
  },
  {
    "id": "vv9204uk",
    "url": "https://www.instagram.com/reel/DMrzdacTmy8/",
    "title": "Instagram",
    "comment": "インスタグラムのテスト",
    "tags": [
      "治安/マナー"
    ],
    "createdAt": 1756116805340,
    "ownerKey": "381f799d-0c46-4c5d-a667-12755a1e0ecb"
  },
  {
    "id": "z4olby4v",
    "media": {
      "type": "image",
      "id": "rnbdm962",
      "url": "/api/posts/media/rnbdm962"
    },
    "title": "画像（ユーザー投稿）",
    "comment": "写真アップロードテスト",
    "tags": [
      "画像"
    ],
    "createdAt": 1756122755429,
    "ownerKey": "381f799d-0c46-4c5d-a667-12755a1e0ecb"
  },
  {
    "id": "ldtzeluz",
    "media": {
      "type": "video",
      "id": "tr44byjj",
      "url": "/api/posts/media/tr44byjj"
    },
    "title": "動画（ユーザー投稿）",
    "comment": "動画アップロードのテスト",
    "tags": [
      "ニュース"
    ],
    "createdAt": 1756123952444,
    "ownerKey": "0db02fca-ef3d-48e2-857e-6043bd88a49a"
  },
  {
    "id": "ukkwnxpp",
    "title": "(無題)",
    "tags": [],
    "createdAt": 1756123961482,
    "ownerKey": "0db02fca-ef3d-48e2-857e-6043bd88a49a"
  }
]